stateset_sandbox/__init__.py
stateset_sandbox/client.py
stateset_sandbox/errors.py
stateset_sandbox/py.typed
stateset_sandbox/types.py
stateset_sandbox-1.0.4.dist-info/METADATA
stateset_sandbox-1.0.4.dist-info/WHEEL
stateset_sandbox-1.0.4.dist-info/RECORD
