Metadata-Version: 2.4
Name: stateset-sandbox
Version: 1.0.4
Summary: Python SDK for the StateSet Sandbox API
Project-URL: Homepage, https://github.com/stateset/sandbox-sdk-python
Project-URL: Documentation, https://docs.stateset.io/sandbox
Project-URL: Repository, https://github.com/stateset/sandbox-sdk-python
Author-email: StateSet <support@stateset.io>
License-Expression: MIT
Keywords: ai,claude,code-execution,sandbox,stateset
Classifier: Development Status :: 4 - Beta
Classifier: Intended Audience :: Developers
Classifier: License :: OSI Approved :: MIT License
Classifier: Programming Language :: Python :: 3
Classifier: Programming Language :: Python :: 3.8
Classifier: Programming Language :: Python :: 3.9
Classifier: Programming Language :: Python :: 3.10
Classifier: Programming Language :: Python :: 3.11
Classifier: Programming Language :: Python :: 3.12
Classifier: Topic :: Software Development :: Libraries :: Python Modules
Requires-Python: >=3.8
Requires-Dist: httpx>=0.24.0
Requires-Dist: pydantic>=2.0.0
Provides-Extra: dev
Requires-Dist: mypy>=1.0.0; extra == 'dev'
Requires-Dist: pytest-asyncio>=0.21.0; extra == 'dev'
Requires-Dist: pytest-httpx>=0.22.0; extra == 'dev'
Requires-Dist: pytest>=7.0.0; extra == 'dev'
Requires-Dist: ruff>=0.1.0; extra == 'dev'
